wgsml/__init__.py
wgsml/data.py
wgsml/feature_selection.py
wgsml-0.1.0.dist-info/METADATA
wgsml-0.1.0.dist-info/WHEEL
wgsml-0.1.0.dist-info/top_level.txt
wgsml-0.1.0.dist-info/RECORD
