Metadata-Version: 2.4
Name: wgsml
Version: 0.1.0
Summary: Library to simplify ML pipelines for whole-genome sequencing data
Author: Ryan Hulke
Requires-Python: >=3.9
Requires-Dist: numpy>=2.3.2
Requires-Dist: torch>=2.6.0
